bcp47/__init__.py
bcp47/bcp47.py
bcp47/generate-bcp47.py
bcp47-0.1.0.dist-info/LICENSE.txt
bcp47-0.1.0.dist-info/METADATA
bcp47-0.1.0.dist-info/WHEEL
bcp47-0.1.0.dist-info/top_level.txt
bcp47-0.1.0.dist-info/RECORD
