Metadata-Version: 2.1
Name: bcp47
Version: 0.1.0
Summary: Language tags made easy
Home-page: https://github.com/highfestiva/bcp47.py
Author: Jonas Byström
Author-email: highfestiva@gmail.com
Classifier: Programming Language :: Python :: 3
Classifier: License :: OSI Approved :: MIT License
Classifier: Operating System :: OS Independent
License-File: LICENSE.txt
